peerbase/__init__.py
peerbase/peer_utils.py
peerbase/relay.py
peerbase-0.6.dist-info/LICENSE
peerbase-0.6.dist-info/METADATA
peerbase-0.6.dist-info/WHEEL
peerbase-0.6.dist-info/top_level.txt
peerbase-0.6.dist-info/RECORD
