Metadata-Version: 2.1
Name: peerbase
Version: 0.6
Summary: High-level p2p protocol allowing both local and remote p2p connections via UDP advertising and a TURN-like middleman server (or multiple)
Home-page: https://github.com/iTecAI/PeerBase
Author: iTecX
Author-email: matteovh@gmail.com
License: MIT
Download-URL: https://github.com/iTecAI/PeerBase/archive/refs/tags/0.6.tar.gz
Keywords: p2p,peer-to-peer,http
Platform: UNKNOWN
Classifier: Development Status :: 3 - Alpha
Classifier: Intended Audience :: Developers
Classifier: Topic :: Software Development :: Build Tools
Classifier: License :: OSI Approved :: MIT License
Classifier: Programming Language :: Python :: 3.8
Classifier: Programming Language :: Python :: 3.9
Requires-Dist: cryptography
Requires-Dist: requests
Requires-Dist: fastapi
Requires-Dist: uvicorn
